odoo/addons/report_layout_config/README.rst
odoo/addons/report_layout_config/__init__.py
odoo/addons/report_layout_config/__manifest__.py
odoo/addons/report_layout_config/data/report_layout.xml
odoo/addons/report_layout_config/i18n/es.po
odoo/addons/report_layout_config/i18n/it.po
odoo/addons/report_layout_config/i18n/report_layout_config.pot
odoo/addons/report_layout_config/models/__init__.py
odoo/addons/report_layout_config/models/base_document_layout.py
odoo/addons/report_layout_config/models/res_company.py
odoo/addons/report_layout_config/readme/CONTRIBUTORS.md
odoo/addons/report_layout_config/readme/DESCRIPTION.md
odoo/addons/report_layout_config/readme/USAGE.md
odoo/addons/report_layout_config/static/description/icon.png
odoo/addons/report_layout_config/static/description/index.html
odoo/addons/report_layout_config/static/img/preview_standard.png
odoo/addons/report_layout_config/static/pdf/preview_standard.pdf
odoo/addons/report_layout_config/static/src/scss/style.scss
odoo/addons/report_layout_config/templates/report_templates.xml
odoo/addons/report_layout_config/views/document_layout.xml
odoo_addon_report_layout_config-17.0.1.0.0.5.dist-info/METADATA
odoo_addon_report_layout_config-17.0.1.0.0.5.dist-info/WHEEL
odoo_addon_report_layout_config-17.0.1.0.0.5.dist-info/top_level.txt
odoo_addon_report_layout_config-17.0.1.0.0.5.dist-info/RECORD
