Metadata-Version: 2.1
Name: odoo-addon-report_layout_config
Version: 17.0.1.0.0.5
Requires-Python: >=3.10
Requires-Dist: odoo>=17.0a,<17.1dev
Summary: Add possibility to easily modify the global report layout
Home-page: https://github.com/OCA/reporting-engine
License: AGPL-3
Author: Camptocamp, Odoo Community Association (OCA)
Author-email: support@odoo-community.org
Classifier: Programming Language :: Python
Classifier: Framework :: Odoo
Classifier: Framework :: Odoo :: 17.0
Classifier: License :: OSI Approved :: GNU Affero General Public License v3
